{
  "ok": true,
  "rows": [
    {
      "sport": "NBA",
      "decided": 137938,
      "paid": 76692,
      "win_rate": 0.5559889225594108,
      "net_dollars": 154460.0
    },
    {
      "sport": "CBB",
      "decided": 55130,
      "paid": 24871,
      "win_rate": 0.4511336840195901,
      "net_dollars": -53880.0
    },
    {
      "sport": "CFB",
      "decided": 0,
      "paid": 0,
      "win_rate": null,
      "net_dollars": 0.0
    },
    {
      "sport": "WNBA",
      "decided": 12749,
      "paid": 5270,
      "win_rate": 0.41336575417679816,
      "net_dollars": -22090.0
    },
    {
      "sport": "MLB",
      "decided": 172004,
      "paid": 51313,
      "win_rate": 0.29832445757075415,
      "net_dollars": -693780.0
    },
    {
      "sport": "SOCCER",
      "decided": 68255,
      "paid": 12806,
      "win_rate": 0.1876199545820819,
      "net_dollars": -426430.0
    },
    {
      "sport": "TENNIS",
      "decided": 10129,
      "paid": 2712,
      "win_rate": 0.2677460756244447,
      "net_dollars": -47050.0
    },
    {
      "sport": "NHL",
      "decided": 56826,
      "paid": 16632,
      "win_rate": 0.2926829268292683,
      "net_dollars": -235620.0
    },
    {
      "sport": "NFL",
      "decided": 0,
      "paid": 0,
      "win_rate": null,
      "net_dollars": 0.0
    }
  ],
  "source": "graded_props_json",
  "signature": "n=100:mt=1780459201259158500"
}