{
  "generated_at": "2026-06-20T11:29:44.088973+00:00",
  "date_range": {
    "min": "2026-02-19",
    "max": "2026-06-19"
  },
  "total_props": 593610,
  "overall_hit_rate": 0.3617,
  "top_slices": [
    {
      "sport": "SOCCER",
      "pick_type": "goblin",
      "direction": "UNDER",
      "tier": "A",
      "hit_rate": 1.0,
      "n": 57,
      "mean_edge": 0.702,
      "priority": 1
    },
    {
      "sport": "NHL",
      "pick_type": "demon",
      "direction": "UNDER",
      "tier": "B",
      "hit_rate": 0.8627,
      "n": 51,
      "mean_edge": 0.209,
      "priority": 2
    },
    {
      "sport": "NBA1Q",
      "pick_type": "goblin",
      "direction": "OVER",
      "tier": "A",
      "hit_rate": 0.8357,
      "n": 2380,
      "mean_edge": 3.554,
      "priority": 3
    },
    {
      "sport": "NHL",
      "pick_type": "demon",
      "direction": "UNDER",
      "tier": "A",
      "hit_rate": 0.8246,
      "n": 228,
      "mean_edge": 0.359,
      "priority": 4
    },
    {
      "sport": "NBA1Q",
      "pick_type": "goblin",
      "direction": "OVER",
      "tier": "B",
      "hit_rate": 0.758,
      "n": 1099,
      "mean_edge": 5.004,
      "priority": 5
    },
    {
      "sport": "NBA1Q",
      "pick_type": "demon",
      "direction": "OVER",
      "tier": "B",
      "hit_rate": 0.7464,
      "n": 138,
      "mean_edge": 1.318,
      "priority": 6
    },
    {
      "sport": "NHL",
      "pick_type": "demon",
      "direction": "UNDER",
      "tier": "D",
      "hit_rate": 0.7453,
      "n": 106,
      "mean_edge": 0.335,
      "priority": 7
    },
    {
      "sport": "NBA1Q",
      "pick_type": "goblin",
      "direction": "OVER",
      "tier": "D",
      "hit_rate": 0.7249,
      "n": 676,
      "mean_edge": 1.208,
      "priority": 8
    },
    {
      "sport": "NHL",
      "pick_type": "standard",
      "direction": "UNDER",
      "tier": "A",
      "hit_rate": 0.7237,
      "n": 2280,
      "mean_edge": -0.849,
      "priority": 9
    },
    {
      "sport": "NHL",
      "pick_type": "standard",
      "direction": "UNDER",
      "tier": "B",
      "hit_rate": 0.7175,
      "n": 669,
      "mean_edge": -0.342,
      "priority": 10
    },
    {
      "sport": "NBA",
      "pick_type": "goblin",
      "direction": "OVER",
      "tier": "A",
      "hit_rate": 0.705,
      "n": 14924,
      "mean_edge": 4.305,
      "priority": 11
    },
    {
      "sport": "NHL",
      "pick_type": "demon",
      "direction": "UNDER",
      "tier": "C",
      "hit_rate": 0.7048,
      "n": 227,
      "mean_edge": 0.114,
      "priority": 12
    },
    {
      "sport": "WNBA",
      "pick_type": "goblin",
      "direction": "OVER",
      "tier": "A",
      "hit_rate": 0.7001,
      "n": 2634,
      "mean_edge": 3.078,
      "priority": 13
    },
    {
      "sport": "NBA1Q",
      "pick_type": "goblin",
      "direction": "OVER",
      "tier": "C",
      "hit_rate": 0.6922,
      "n": 757,
      "mean_edge": 3.117,
      "priority": 14
    },
    {
      "sport": "NBA",
      "pick_type": "goblin",
      "direction": "OVER",
      "tier": "B",
      "hit_rate": 0.6757,
      "n": 9991,
      "mean_edge": 3.759,
      "priority": 15
    },
    {
      "sport": "MLB",
      "pick_type": "goblin",
      "direction": "OVER",
      "tier": "C",
      "hit_rate": 0.6683,
      "n": 5002,
      "mean_edge": 0.961,
      "priority": 16
    },
    {
      "sport": "TENNIS",
      "pick_type": "standard",
      "direction": "UNDER",
      "tier": "D",
      "hit_rate": 0.6636,
      "n": 107,
      "mean_edge": -6.825,
      "priority": 17
    },
    {
      "sport": "SOCCER",
      "pick_type": "goblin",
      "direction": "UNDER",
      "tier": "D",
      "hit_rate": 0.6634,
      "n": 101,
      "mean_edge": 0.332,
      "priority": 18
    },
    {
      "sport": "NBA1Q",
      "pick_type": "demon",
      "direction": "OVER",
      "tier": "A",
      "hit_rate": 0.6633,
      "n": 196,
      "mean_edge": 1.233,
      "priority": 19
    },
    {
      "sport": "NHL",
      "pick_type": "standard",
      "direction": "UNDER",
      "tier": "C",
      "hit_rate": 0.6615,
      "n": 257,
      "mean_edge": 0.076,
      "priority": 20
    },
    {
      "sport": "NBA1Q",
      "pick_type": "standard",
      "direction": "OVER",
      "tier": "C",
      "hit_rate": 0.6522,
      "n": 92,
      "mean_edge": 6.317,
      "priority": 21
    },
    {
      "sport": "NBA",
      "pick_type": "goblin",
      "direction": "OVER",
      "tier": "C",
      "hit_rate": 0.6512,
      "n": 11658,
      "mean_edge": 3.238,
      "priority": 22
    },
    {
      "sport": "CBB",
      "pick_type": "goblin",
      "direction": "OVER",
      "tier": "B",
      "hit_rate": 0.6499,
      "n": 1685,
      "mean_edge": 2.363,
      "priority": 23
    },
    {
      "sport": "CBB",
      "pick_type": "goblin",
      "direction": "OVER",
      "tier": "A",
      "hit_rate": 0.6416,
      "n": 1727,
      "mean_edge": 4.216,
      "priority": 24
    },
    {
      "sport": "NBA1Q",
      "pick_type": "standard",
      "direction": "OVER",
      "tier": "A",
      "hit_rate": 0.6401,
      "n": 992,
      "mean_edge": 2.409,
      "priority": 25
    }
  ],
  "avoid_slices": [
    {
      "sport": "SOCCER",
      "pick_type": "standard",
      "direction": "OVER",
      "tier": "C",
      "hit_rate": 0.1008,
      "n": 1339,
      "mean_edge": -0.554,
      "priority": 1
    },
    {
      "sport": "TENNIS",
      "pick_type": "demon",
      "direction": "OVER",
      "tier": "D",
      "hit_rate": 0.1337,
      "n": 6595,
      "mean_edge": -2.892,
      "priority": 2
    },
    {
      "sport": "SOCCER",
      "pick_type": "standard",
      "direction": "OVER",
      "tier": "D",
      "hit_rate": 0.1409,
      "n": 22453,
      "mean_edge": -0.892,
      "priority": 3
    },
    {
      "sport": "MLB",
      "pick_type": "demon",
      "direction": "OVER",
      "tier": "C",
      "hit_rate": 0.1458,
      "n": 2291,
      "mean_edge": -3.175,
      "priority": 4
    },
    {
      "sport": "MLB",
      "pick_type": "demon",
      "direction": "OVER",
      "tier": "B",
      "hit_rate": 0.1599,
      "n": 9675,
      "mean_edge": -2.13,
      "priority": 5
    },
    {
      "sport": "WNBA",
      "pick_type": "demon",
      "direction": "OVER",
      "tier": "D",
      "hit_rate": 0.1634,
      "n": 3348,
      "mean_edge": -5.89,
      "priority": 6
    },
    {
      "sport": "SOCCER",
      "pick_type": "standard",
      "direction": "OVER",
      "tier": "A",
      "hit_rate": 0.1711,
      "n": 4442,
      "mean_edge": -0.655,
      "priority": 7
    },
    {
      "sport": "SOCCER",
      "pick_type": "demon",
      "direction": "OVER",
      "tier": "D",
      "hit_rate": 0.1887,
      "n": 26353,
      "mean_edge": -0.86,
      "priority": 8
    },
    {
      "sport": "NHL",
      "pick_type": "demon",
      "direction": "OVER",
      "tier": "B",
      "hit_rate": 0.1991,
      "n": 211,
      "mean_edge": -0.11,
      "priority": 9
    },
    {
      "sport": "MLB",
      "pick_type": "demon",
      "direction": "OVER",
      "tier": "D",
      "hit_rate": 0.2093,
      "n": 169196,
      "mean_edge": -0.925,
      "priority": 10
    }
  ],
  "prop_type_rankings": [
    {
      "prop_type": "Goals",
      "direction": "UNDER",
      "hit_rate": 0.7572,
      "n": 2376,
      "mean_edge": 0.484
    },
    {
      "prop_type": "Shots",
      "direction": "UNDER",
      "hit_rate": 0.6765,
      "n": 544,
      "mean_edge": 0.362
    },
    {
      "prop_type": "Time On Ice",
      "direction": "UNDER",
      "hit_rate": 0.6569,
      "n": 443,
      "mean_edge": 0.122
    },
    {
      "prop_type": "fantasy",
      "direction": "OVER",
      "hit_rate": 0.6273,
      "n": 110,
      "mean_edge": 5.112
    },
    {
      "prop_type": "stl",
      "direction": "OVER",
      "hit_rate": 0.6176,
      "n": 387,
      "mean_edge": 0.591
    },
    {
      "prop_type": "ast",
      "direction": "OVER",
      "hit_rate": 0.6164,
      "n": 610,
      "mean_edge": 0.88
    },
    {
      "prop_type": "Assists",
      "direction": "UNDER",
      "hit_rate": 0.6155,
      "n": 2034,
      "mean_edge": -0.594
    },
    {
      "prop_type": "Fantasy Score",
      "direction": "OVER",
      "hit_rate": 0.6106,
      "n": 5303,
      "mean_edge": 5.88
    },
    {
      "prop_type": "ra",
      "direction": "UNDER",
      "hit_rate": 0.6104,
      "n": 231,
      "mean_edge": -0.699
    },
    {
      "prop_type": "reb",
      "direction": "UNDER",
      "hit_rate": 0.6103,
      "n": 195,
      "mean_edge": -0.508
    },
    {
      "prop_type": "Steals",
      "direction": "UNDER",
      "hit_rate": 0.6074,
      "n": 242,
      "mean_edge": -0.193
    },
    {
      "prop_type": "fg3m",
      "direction": "OVER",
      "hit_rate": 0.6022,
      "n": 357,
      "mean_edge": 0.682
    },
    {
      "prop_type": "ast",
      "direction": "UNDER",
      "hit_rate": 0.6,
      "n": 70,
      "mean_edge": -0.287
    },
    {
      "prop_type": "Plus/Minus",
      "direction": "UNDER",
      "hit_rate": 0.6,
      "n": 210,
      "mean_edge": 0.407
    },
    {
      "prop_type": "time_on_ice",
      "direction": "OVER",
      "hit_rate": 0.5988,
      "n": 162,
      "mean_edge": 0.78
    },
    {
      "prop_type": "pts",
      "direction": "OVER",
      "hit_rate": 0.585,
      "n": 1535,
      "mean_edge": 2.407
    },
    {
      "prop_type": "reb",
      "direction": "OVER",
      "hit_rate": 0.5786,
      "n": 942,
      "mean_edge": 1.007
    },
    {
      "prop_type": "Plate Appearances",
      "direction": "UNDER",
      "hit_rate": 0.5783,
      "n": 83,
      "mean_edge": -2.748
    },
    {
      "prop_type": "Turnovers",
      "direction": "UNDER",
      "hit_rate": 0.5718,
      "n": 404,
      "mean_edge": -0.334
    },
    {
      "prop_type": "tov",
      "direction": "OVER",
      "hit_rate": 0.5595,
      "n": 227,
      "mean_edge": 0.339
    },
    {
      "prop_type": "—",
      "direction": "UNDER",
      "hit_rate": 0.5566,
      "n": 3965,
      "mean_edge": -1.252
    },
    {
      "prop_type": "Singles",
      "direction": "UNDER",
      "hit_rate": 0.5554,
      "n": 722,
      "mean_edge": -0.222
    },
    {
      "prop_type": "Rebs+Asts",
      "direction": "UNDER",
      "hit_rate": 0.5543,
      "n": 911,
      "mean_edge": -1.052
    },
    {
      "prop_type": "pr",
      "direction": "UNDER",
      "hit_rate": 0.553,
      "n": 349,
      "mean_edge": -1.452
    },
    {
      "prop_type": "Total Games Won",
      "direction": "UNDER",
      "hit_rate": 0.5489,
      "n": 133,
      "mean_edge": -5.435
    },
    {
      "prop_type": "Pitches Thrown",
      "direction": "UNDER",
      "hit_rate": 0.5472,
      "n": 360,
      "mean_edge": -6.291
    },
    {
      "prop_type": "Runs",
      "direction": "UNDER",
      "hit_rate": 0.5469,
      "n": 715,
      "mean_edge": -0.22
    },
    {
      "prop_type": "pa",
      "direction": "UNDER",
      "hit_rate": 0.5435,
      "n": 276,
      "mean_edge": -1.249
    },
    {
      "prop_type": "Total Bases",
      "direction": "UNDER",
      "hit_rate": 0.538,
      "n": 842,
      "mean_edge": -0.314
    },
    {
      "prop_type": "Hits",
      "direction": "UNDER",
      "hit_rate": 0.5373,
      "n": 2308,
      "mean_edge": -0.218
    },
    {
      "prop_type": "Pts+Asts",
      "direction": "OVER",
      "hit_rate": 0.5369,
      "n": 11632,
      "mean_edge": 2.846
    },
    {
      "prop_type": "blk",
      "direction": "OVER",
      "hit_rate": 0.5357,
      "n": 140,
      "mean_edge": 0.583
    },
    {
      "prop_type": "Rebounds",
      "direction": "UNDER",
      "hit_rate": 0.5343,
      "n": 2912,
      "mean_edge": -1.937
    },
    {
      "prop_type": "Points",
      "direction": "UNDER",
      "hit_rate": 0.5342,
      "n": 6222,
      "mean_edge": -2.47
    },
    {
      "prop_type": "Blocks",
      "direction": "UNDER",
      "hit_rate": 0.5341,
      "n": 616,
      "mean_edge": 0.208
    },
    {
      "prop_type": "Strikeouts",
      "direction": "UNDER",
      "hit_rate": 0.5337,
      "n": 1810,
      "mean_edge": -0.496
    },
    {
      "prop_type": "Turnovers",
      "direction": "OVER",
      "hit_rate": 0.5331,
      "n": 2459,
      "mean_edge": 0.39
    },
    {
      "prop_type": "Pitcher Fantasy Score",
      "direction": "UNDER",
      "hit_rate": 0.533,
      "n": 197,
      "mean_edge": -4.686
    },
    {
      "prop_type": "Steals",
      "direction": "OVER",
      "hit_rate": 0.5326,
      "n": 4129,
      "mean_edge": 0.435
    },
    {
      "prop_type": "FG Attempted",
      "direction": "UNDER",
      "hit_rate": 0.5322,
      "n": 1103,
      "mean_edge": -1.388
    }
  ],
  "player_rankings": {
    "top_30": [
      {
        "player": "Brad Stuver",
        "sport": "SOCCER",
        "hit_rate": 1.0,
        "n": 24,
        "primary_prop_type": "Goals",
        "consistency": 1.0
      },
      {
        "player": "Ja'Kobe Walter",
        "sport": "NBA1Q",
        "hit_rate": 0.963,
        "n": 27,
        "primary_prop_type": "Points",
        "consistency": 0.811
      },
      {
        "player": "Bryce McGowens",
        "sport": "NBA",
        "hit_rate": 0.9565,
        "n": 23,
        "primary_prop_type": "Points",
        "consistency": 0.796
      },
      {
        "player": "Donte DiVincenzo",
        "sport": "NBA1Q",
        "hit_rate": 0.9211,
        "n": 38,
        "primary_prop_type": "Points",
        "consistency": 0.73
      },
      {
        "player": "Micah Potter",
        "sport": "NBA",
        "hit_rate": 0.9,
        "n": 40,
        "primary_prop_type": "Points",
        "consistency": 0.7
      },
      {
        "player": "Royce O'Neale",
        "sport": "NBA1Q",
        "hit_rate": 0.9,
        "n": 20,
        "primary_prop_type": "Points",
        "consistency": 0.7
      },
      {
        "player": "Sam Hauser",
        "sport": "NBA1Q",
        "hit_rate": 0.8913,
        "n": 46,
        "primary_prop_type": "Points",
        "consistency": 0.689
      },
      {
        "player": "Jamir Watkins",
        "sport": "NBA",
        "hit_rate": 0.8696,
        "n": 23,
        "primary_prop_type": "Points",
        "consistency": 0.663
      },
      {
        "player": "Jonathan Kuminga",
        "sport": "NBA1Q",
        "hit_rate": 0.8636,
        "n": 22,
        "primary_prop_type": "Points",
        "consistency": 0.657
      },
      {
        "player": "Michael Imariagbe",
        "sport": "CBB",
        "hit_rate": 0.8636,
        "n": 22,
        "primary_prop_type": "—",
        "consistency": 0.657
      },
      {
        "player": "Obi Toppin",
        "sport": "NBA",
        "hit_rate": 0.859,
        "n": 78,
        "primary_prop_type": "Points",
        "consistency": 0.652
      },
      {
        "player": "Akai Fleming",
        "sport": "CBB",
        "hit_rate": 0.8571,
        "n": 21,
        "primary_prop_type": "—",
        "consistency": 0.65
      },
      {
        "player": "Thijs De Ridder",
        "sport": "CBB",
        "hit_rate": 0.85,
        "n": 20,
        "primary_prop_type": "—",
        "consistency": 0.643
      },
      {
        "player": "Andrew McKeever",
        "sport": "CBB",
        "hit_rate": 0.85,
        "n": 20,
        "primary_prop_type": "—",
        "consistency": 0.643
      },
      {
        "player": "Izaiyah Nelson",
        "sport": "CBB",
        "hit_rate": 0.8421,
        "n": 38,
        "primary_prop_type": "—",
        "consistency": 0.635
      },
      {
        "player": "LaMelo Ball",
        "sport": "NBA1Q",
        "hit_rate": 0.8286,
        "n": 35,
        "primary_prop_type": "Points",
        "consistency": 0.623
      },
      {
        "player": "Jaxson Hayes",
        "sport": "NBA1Q",
        "hit_rate": 0.8261,
        "n": 23,
        "primary_prop_type": "Rebounds",
        "consistency": 0.621
      },
      {
        "player": "Brian Rodríguez",
        "sport": "SOCCER",
        "hit_rate": 0.8261,
        "n": 23,
        "primary_prop_type": "Shots",
        "consistency": 0.621
      },
      {
        "player": "Cameron Johnson",
        "sport": "NBA1Q",
        "hit_rate": 0.8235,
        "n": 51,
        "primary_prop_type": "Points",
        "consistency": 0.619
      },
      {
        "player": "Mikal Bridges",
        "sport": "NBA1H",
        "hit_rate": 0.8182,
        "n": 33,
        "primary_prop_type": "Points",
        "consistency": 0.614
      },
      {
        "player": "Jase Butler",
        "sport": "CBB",
        "hit_rate": 0.8095,
        "n": 21,
        "primary_prop_type": "—",
        "consistency": 0.607
      },
      {
        "player": "Jorge Diaz Graham",
        "sport": "CBB",
        "hit_rate": 0.8095,
        "n": 21,
        "primary_prop_type": "—",
        "consistency": 0.607
      },
      {
        "player": "Isaac Celiscar",
        "sport": "CBB",
        "hit_rate": 0.8065,
        "n": 31,
        "primary_prop_type": "—",
        "consistency": 0.605
      },
      {
        "player": "Leonard Miller",
        "sport": "NBA",
        "hit_rate": 0.8065,
        "n": 62,
        "primary_prop_type": "Points",
        "consistency": 0.605
      },
      {
        "player": "Tarence Guinyard",
        "sport": "CBB",
        "hit_rate": 0.7917,
        "n": 24,
        "primary_prop_type": "—",
        "consistency": 0.594
      },
      {
        "player": "Kyle Anderson",
        "sport": "NBA",
        "hit_rate": 0.7879,
        "n": 33,
        "primary_prop_type": "Rebounds",
        "consistency": 0.591
      },
      {
        "player": "David Dixon",
        "sport": "CBB",
        "hit_rate": 0.7857,
        "n": 28,
        "primary_prop_type": "—",
        "consistency": 0.59
      },
      {
        "player": "Marko Dmitrovic",
        "sport": "SOCCER",
        "hit_rate": 0.7826,
        "n": 23,
        "primary_prop_type": "Goals",
        "consistency": 0.588
      },
      {
        "player": "Andrew Nembhard",
        "sport": "NBA",
        "hit_rate": 0.782,
        "n": 211,
        "primary_prop_type": "Pts+Rebs+Asts",
        "consistency": 0.587
      },
      {
        "player": "Scottie Barnes",
        "sport": "NBA1H",
        "hit_rate": 0.7778,
        "n": 27,
        "primary_prop_type": "Points",
        "consistency": 0.584
      }
    ],
    "bottom_20": [
      {
        "player": "Leon Bailey",
        "sport": "SOCCER",
        "hit_rate": 0.0,
        "n": 39,
        "primary_prop_type": "Shots"
      },
      {
        "player": "Liam Millar",
        "sport": "SOCCER",
        "hit_rate": 0.0,
        "n": 30,
        "primary_prop_type": "Shots"
      },
      {
        "player": "Filip Marchwinski",
        "sport": "SOCCER",
        "hit_rate": 0.0,
        "n": 27,
        "primary_prop_type": "Shots"
      },
      {
        "player": "Tanner Beason",
        "sport": "SOCCER",
        "hit_rate": 0.0,
        "n": 23,
        "primary_prop_type": "Shots"
      },
      {
        "player": "Marcelino Núñez",
        "sport": "SOCCER",
        "hit_rate": 0.0,
        "n": 22,
        "primary_prop_type": "Shots"
      },
      {
        "player": "Griffin Dillon",
        "sport": "SOCCER",
        "hit_rate": 0.0,
        "n": 22,
        "primary_prop_type": "Shots"
      },
      {
        "player": "Nahuel Estévez",
        "sport": "SOCCER",
        "hit_rate": 0.0,
        "n": 20,
        "primary_prop_type": "Shots"
      },
      {
        "player": "Jonas Hofmann",
        "sport": "SOCCER",
        "hit_rate": 0.0,
        "n": 26,
        "primary_prop_type": "Shots"
      },
      {
        "player": "Mitchel Bakker",
        "sport": "SOCCER",
        "hit_rate": 0.0,
        "n": 31,
        "primary_prop_type": "Shots"
      },
      {
        "player": "Nathan Patterson",
        "sport": "SOCCER",
        "hit_rate": 0.0,
        "n": 20,
        "primary_prop_type": "Shots"
      },
      {
        "player": "Nelson Weiper",
        "sport": "SOCCER",
        "hit_rate": 0.0,
        "n": 22,
        "primary_prop_type": "Shots"
      },
      {
        "player": "Moi Gómez",
        "sport": "SOCCER",
        "hit_rate": 0.0,
        "n": 31,
        "primary_prop_type": "Shots"
      },
      {
        "player": "Johan Bakayoko",
        "sport": "SOCCER",
        "hit_rate": 0.0,
        "n": 26,
        "primary_prop_type": "Shots"
      },
      {
        "player": "Alejandro Bedoya",
        "sport": "SOCCER",
        "hit_rate": 0.0,
        "n": 26,
        "primary_prop_type": "Shots"
      },
      {
        "player": "Alejandro Balde",
        "sport": "SOCCER",
        "hit_rate": 0.0,
        "n": 29,
        "primary_prop_type": "Shots"
      },
      {
        "player": "Tahir Reid-Brown",
        "sport": "SOCCER",
        "hit_rate": 0.0,
        "n": 20,
        "primary_prop_type": "Shots"
      },
      {
        "player": "Will Reilly",
        "sport": "SOCCER",
        "hit_rate": 0.0,
        "n": 25,
        "primary_prop_type": "Shots"
      },
      {
        "player": "Johan Vásquez",
        "sport": "SOCCER",
        "hit_rate": 0.0,
        "n": 21,
        "primary_prop_type": "Shots"
      },
      {
        "player": "Hosei Kijima",
        "sport": "SOCCER",
        "hit_rate": 0.0,
        "n": 22,
        "primary_prop_type": "Shots"
      },
      {
        "player": "Alex Murphy",
        "sport": "SOCCER",
        "hit_rate": 0.0,
        "n": 21,
        "primary_prop_type": "Shots"
      }
    ]
  },
  "edge_correlations": {
    "per_sport": {
      "CBB": -0.08451462940815117,
      "MLB": -0.061180737113995215,
      "NBA": 0.10370646201762278,
      "NBA1H": -0.06260353757825698,
      "NBA1Q": -0.07716192232544238,
      "NHL": 0.01765971954496329,
      "SOCCER": -0.05701630974641365,
      "TENNIS": 0.016808608074669454,
      "WNBA": -0.05632649443434162
    },
    "strongest_sport": "NBA",
    "strongest_r": 0.10370646201762278,
    "monotonic": false,
    "avg_r": -0.028958760107705053,
    "verdict": "NO"
  },
  "streak_signals": {
    "verdict": "YES",
    "hot_hr": 0.636350349661881,
    "cold_hr": 0.2897187629933123,
    "best_streak_signal": "TENNIS UNDER"
  }
}